kathimeripy/__init__.py
kathimeripy/__main__.py
kathimeripy-0.7.1.dist-info/LICENSE
kathimeripy-0.7.1.dist-info/METADATA
kathimeripy-0.7.1.dist-info/WHEEL
kathimeripy-0.7.1.dist-info/RECORD
