Metadata-Version: 2.1
Name: kathimeripy
Version: 0.7.1
Summary: A package that uses you user name and password for Kathimerini.gr to generate an Epub and send it to your Amazon Kindle.
License: MIT
Author: Kdra
Author-email: drakopuloskostas+gh@gmail.com
Requires-Python: >=3.12,<4.0
Classifier: License :: OSI Approved :: MIT License
Classifier: Programming Language :: Python :: 3
Classifier: Programming Language :: Python :: 3.12
Classifier: Programming Language :: Python :: 3.13
Classifier: Topic :: Office/Business :: News/Diary
Requires-Dist: beautifulsoup4 (>=4.12.3,<5.0.0)
Requires-Dist: datetime (>=5.5,<6.0)
Requires-Dist: epub (>=0.5.2,<0.6.0)
Requires-Dist: joblib (>=1.4.2,<2.0.0)
Requires-Dist: pypub3 (>=2.0.7,<3.0.0)
Requires-Dist: python-crontab (>=3.2.0,<4.0.0)
Requires-Dist: requests (>=2.32.3,<3.0.0)
Requires-Dist: rss-parser (>=2.1.0,<3.0.0)
Requires-Dist: typer (>=0.15.1,<0.16.0)
